LICENSE
README.md
setup.cfg
setup.py
flextrade/__init__.py
flextrade/enum.py
flextrade/flextrade_client.py
flextrade/abis/AdaptiveFeeCalculator.json
flextrade/abis/CIXPriceAdapter.json
flextrade/abis/CalcPricelens.json
flextrade/abis/Calculator.json
flextrade/abis/ConfigStorage.json
flextrade/abis/CrossMarginHandler.json
flextrade/abis/ERC20.json
flextrade/abis/GlpManager.json
flextrade/abis/GmPriceAdapter.json
flextrade/abis/LimitTradeHandler.json
flextrade/abis/OnchainPricelens.json
flextrade/abis/OrderbookOracle.json
flextrade/abis/PerpStorage.json
flextrade/abis/TradeHelper.json
flextrade/abis/VaultStorage.json
flextrade/constants/__init__.py
flextrade/constants/assets.py
flextrade/constants/common.py
flextrade/constants/contracts.py
flextrade/constants/intent.py
flextrade/constants/markets.py
flextrade/constants/pricefeed.py
flextrade/constants/tokens.py
flextrade/helpers/__init__.py
flextrade/helpers/contract_loader.py
flextrade/helpers/mapper.py
flextrade/helpers/util.py
flextrade/modules/__init__.py
flextrade/modules/private.py
flextrade/modules/public.py
flextrade/modules/calculator/__init__.py
flextrade/modules/calculator/calculator.py
flextrade/modules/oracle/__init__.py
flextrade/modules/oracle/oracle_middleware.py
flextrade/modules/oracle/calc_pricelens_oracle/__init__.py
flextrade/modules/oracle/calc_pricelens_oracle/calc_pricelens_oracle.py
flextrade/modules/oracle/cix_oracle/__init__.py
flextrade/modules/oracle/cix_oracle/cix_oracle.py
flextrade/modules/oracle/glp_oracle/__init__.py
flextrade/modules/oracle/glp_oracle/glp_oracle.py
flextrade/modules/oracle/gm_oracle/__init__.py
flextrade/modules/oracle/gm_oracle/gm_oracle.py
flextrade/modules/oracle/onchain_pricelens_oracle/__init__.py
flextrade/modules/oracle/onchain_pricelens_oracle/onchain_pricelen_oracle.py
flextrade/modules/oracle/pyth_oracle/__init__.py
flextrade/modules/oracle/pyth_oracle/pyth_oracle.py
fp_v2_python.egg-info/PKG-INFO
fp_v2_python.egg-info/SOURCES.txt
fp_v2_python.egg-info/dependency_links.txt
fp_v2_python.egg-info/requires.txt
fp_v2_python.egg-info/top_level.txt
tests/__init__.py
tests/constants.py
tests/test_create_market_order.py
